MANIFEST.in
README.txt
setup.py
flayers/__init__.py
flayers/flayers.cpp
flayers/flayers.h
flayers/flayers.i
flayers/flayers.py
flayers/flayers_wrap.cxx
flayers/metainfos.py
flayers.egg-info/PKG-INFO
flayers.egg-info/SOURCES.txt
flayers.egg-info/dependency_links.txt
flayers.egg-info/native_libs.txt
flayers.egg-info/top_level.txt
flayers/src/ArgvParser.cpp
flayers/src/ArgvParser.h
flayers/src/ArgvParserContainer.cpp
flayers/src/ArgvParserContainer.h
flayers/src/ClassTopology.cpp
flayers/src/ClassTopology.h
flayers/src/IncBoostTrainer.cpp
flayers/src/IncBoostTrainer.h
flayers/src/InsideTopology.h
flayers/src/Layer.cpp
flayers/src/Layer.h
flayers/src/LinearRegressor.cpp
flayers/src/LinearRegressor.h
flayers/src/NNLayer.cpp
flayers/src/NNLayer.h
flayers/src/OptTopology.cpp
flayers/src/OptTopology.h
flayers/src/PreDefArgvParser.cpp
flayers/src/PreDefArgvParser.h
flayers/src/Topology.cpp
flayers/src/Topology.h
flayers/src/Trainer.cpp
flayers/src/Trainer.h
flayers/src/TrainerUtil.cpp
flayers/src/TrainerUtil.h
flayers/src/TwoDSurfaceData.cpp
flayers/src/TwoDSurfaceData.h
flayers/src/Weights.cpp
flayers/src/Weights.h
flayers/src/WeightsList.cpp
flayers/src/WeightsList.h
flayers/src/fDataSet.cpp
flayers/src/fDataSet.h
flayers/src/fLayersGeneral.cpp
flayers/src/fLayersGeneral.h
flayers/src/fTimeMeasurer.cpp
flayers/src/fTimeMeasurer.h
flayers/src/general.h
flayers/src/math_util.cpp
flayers/src/math_util.h