Metadata-Version: 1.0
Name: flayers
Version: 2.6
Summary: python flayers wrapper interface
Home-page: http://sourceforge.net/projects/mlboost/
Author: Francis Pieraut
Author-email: fpieraut@gmail.com
License: AGPL v3 or later
Platform: UNKNOWN
